javascript/__init__.py
javascript/__main__.py
javascript/config.py
javascript/connection.py
javascript/errors.py
javascript/events.py
javascript/json_patch.py
javascript/proxy.py
javascript/pyi.py
javascript/js/bridge.js
javascript/js/deps.js
javascript/js/errors.js
javascript/js/pyi.js
websocket_javascript-1!1.2.1.dist-info/LICENSE
websocket_javascript-1!1.2.1.dist-info/METADATA
websocket_javascript-1!1.2.1.dist-info/WHEEL
websocket_javascript-1!1.2.1.dist-info/top_level.txt
websocket_javascript-1!1.2.1.dist-info/RECORD
