Metadata-Version: 2.1
Name: websocket_javascript
Version: 1!1.2.1
Summary: Call and interop Node.js APIs with Python
Home-page: https://github.com/shuyabin/JSPyBridge
Author: shuyabin
Author-email: extreme@protonmail.ch
Project-URL: Bug Reports, https://github.com/extremeheat/JSPyBridge/issues
Project-URL: Say Thanks!, https://github.com/extremeheat/JSPyBridge
Project-URL: Source, https://github.com/extremeheat/JSPyBridge/
Keywords: node,javascript,bridge,development
Classifier: Development Status :: 3 - Alpha
Classifier: Intended Audience :: Developers
Classifier: Topic :: Software Development :: Build Tools
Classifier: License :: OSI Approved :: MIT License
Classifier: Programming Language :: Python :: 3
Classifier: Programming Language :: Python :: 3.7
Classifier: Programming Language :: Python :: 3.8
Classifier: Programming Language :: Python :: 3.9
Classifier: Programming Language :: Python :: 3 :: Only
Requires-Python: >=3.7, <4
License-File: LICENSE
Provides-Extra: dev
Requires-Dist: check-manifest ; extra == 'dev'
Provides-Extra: test
Requires-Dist: coverage ; extra == 'test'
